LICENSE.txt
README.md
setup.py
codigofranco/__init__.py
codigofranco/__main__.py
codigofranco/config.py
codigofranco/workshops.py
codigofranco.egg-info/PKG-INFO
codigofranco.egg-info/SOURCES.txt
codigofranco.egg-info/dependency_links.txt
codigofranco.egg-info/entry_points.txt
codigofranco.egg-info/requires.txt
codigofranco.egg-info/top_level.txt