Metadata-Version: 2.1
Name: codigofranco
Version: 0.0.2
Summary: Permite consumir el API de CódigoFacilito
Home-page: https://github.com/Jafrazar/codigopython_package
Author: Jaime Franco Del Alcazar Flores
Author-email: frank43_8@hotmail.com
License: MIT
Keywords: codigofacilito
Platform: UNKNOWN
Classifier: Development Status :: 3 - Alpha
Classifier: Intended Audience :: Developers
Classifier: Topic :: Software Development :: Build Tools
Classifier: License :: OSI Approved :: MIT License
Classifier: Programming Language :: Python :: 3
License-File: LICENSE.txt
